tlopo_command/__init__.py
tlopo_command/command.py
tlopo_command-0.1.0.dist-info/METADATA
tlopo_command-0.1.0.dist-info/WHEEL
tlopo_command-0.1.0.dist-info/top_level.txt
tlopo_command-0.1.0.dist-info/RECORD
