Metadata-Version: 2.1
Name: tlopo-command
Version: 0.1.0
Summary: Run shell commands with a nice api
Home-page: UNKNOWN
Author: UNKNOWN
Author-email: UNKNOWN
License: UNKNOWN
Platform: UNKNOWN
